{"last_sync":"03.02.2021, 12:25 Uhr","books":[{"mediaNum":"12020185","mediaType":"book","isbn":"3-7857-2684-8","author":"Miller, Hanna","title":"Denn das Leben ist eine Reise","numBorrowed":7,"borrowedAt":"02.02.2021"},{"mediaNum":"12020148","mediaType":"book","isbn":"3-86612-486-4","author":"Förg, Nicola","title":"Flüsternde Wälder","numBorrowed":6,"borrowedAt":"25.01.2021"},{"mediaNum":"12020132","mediaType":"book","isbn":"3-328-10402-X","author":"Sandberg, Ellen","title":"Das Erbe","numBorrowed":6,"borrowedAt":"12.01.2021"},{"mediaNum":"12020135","mediaType":"book","isbn":"3-442-75783-5","author":"Aichner, Bernhard","title":"Der Fund","numBorrowed":6,"borrowedAt":"22.12.2020"},{"mediaNum":"12020147","mediaType":"book","isbn":"3-499-26792-6","author":"Moyes, Jojo","title":"Der Klang des Herzens","numBorrowed":6,"borrowedAt":"24.11.2020"},{"mediaNum":"12020030","mediaType":"book","isbn":"3-442-31505-0","author":"Robotham, Michael","title":"Schweige still / Cyrus Haven Bd. 1","numBorrowed":6,"borrowedAt":"08.09.2020"},{"mediaNum":"12020248","mediaType":"book","isbn":"3-7408-0825-X","author":"Tischlinger, Martina","title":"Camping mit Mord","numBorrowed":5,"borrowedAt":"12.01.2021"},{"mediaNum":"12019261","mediaType":"book","isbn":"3-455-00546-2","author":"Conti, Giulia","title":"Lago Mortale","numBorrowed":5,"borrowedAt":"12.01.2021"},{"mediaNum":"12020033","mediaType":"book","isbn":"3-458-36454-4","author":"Moggach, Deborah","title":"Die Liebe einer Tochter","numBorrowed":5,"borrowedAt":"09.12.2020"},{"mediaNum":"12019098","mediaType":"book","isbn":"3-442-48738-2","author":"Walsh, Rosie","title":"Ohne ein einziges Wort","numBorrowed":5,"borrowedAt":"03.11.2020"},{"mediaNum":"12019314","mediaType":"book","isbn":"3-7466-3657-4","author":"Sarenbrant, Sofie","title":"Hinter deinem Rücken","numBorrowed":5,"borrowedAt":"15.10.2020"},{"mediaNum":"12019247","mediaType":"book","isbn":"3-426-30718-9","author":"Kliesch, Vincent","title":"Auris","numBorrowed":5,"borrowedAt":"15.10.2020"},{"mediaNum":"12020034","mediaType":"book","isbn":"3-499-27622-4","author":"Ashton, Juliet","title":"Der Sunday Lunch Club","numBorrowed":5,"borrowedAt":"01.10.2020"},{"mediaNum":"12020284","mediaType":"book","isbn":"3-550-08180-4","author":"Klüpfel, Volker / Kobr, Michael","title":"Funkenmord","numBorrowed":4,"borrowedAt":"02.02.2021"},{"mediaNum":"12020274","mediaType":"book","isbn":"3-7857-2670-8","author":"Völler, Eva","title":"Ein Traum vom Glück - Ruhrpott-Saga Bd. 1","numBorrowed":4,"borrowedAt":"01.02.2021"},{"mediaNum":"12017017","mediaType":"book","isbn":"3-442-31396-1","author":"Riley, Lucinda","title":"Die Schattenschwester","numBorrowed":4,"borrowedAt":"27.01.2021"},{"mediaNum":"12020297","mediaType":"book","isbn":"3-596-70029-9","author":"Kirsch, Lisa","title":"Das Glück in vollen Zügen","numBorrowed":4,"borrowedAt":"24.01.2021"},{"mediaNum":"12020172","mediaType":"book","isbn":"3-492-06155-9","author":"Cooper, Roxie","title":"Kein Jahr ohne dich","numBorrowed":4,"borrowedAt":"24.01.2021"},{"mediaNum":"12020007","mediaType":"book","isbn":"3-596-29919-5","author":"Wolf, Klaus-Peter","title":"Totentanz am Strand","numBorrowed":4,"borrowedAt":"19.01.2021"},{"mediaNum":"12020264","mediaType":"book","isbn":"3-426-52197-0","author":"Martin, Pierre","title":"Madame le Commissaire und die tote Nonne","numBorrowed":4,"borrowedAt":"12.01.2021"},{"mediaNum":"12020032","mediaType":"book","isbn":"3-426-65447-4","author":"Föhr, Andreas","title":"Tote Hand","numBorrowed":4,"borrowedAt":"12.01.2021"},{"mediaNum":"12020252","mediaType":"book","isbn":"3-548-06434-5","author":"Bergmann, Renate","title":"Dann bleiben wir eben zu Hause","numBorrowed":4,"borrowedAt":"26.12.2020"},{"mediaNum":"12020131","mediaType":"book","isbn":"3-492-30740-X","author":"Münzer, Hanni","title":"Unter Wasser kann man nicht weinen","numBorrowed":4,"borrowedAt":"22.12.2020"},{"mediaNum":"12020180","mediaType":"book","isbn":"3-453-36045-1","author":"Guggisberg, Brigitte","title":"Die Weinbergfrauen","numBorrowed":4,"borrowedAt":"18.12.2020"},{"mediaNum":"12020166","mediaType":"book","isbn":"3-446-26419-1","author":"Owens, Delia","title":"Der Gesang der Flusskrebse","numBorrowed":4,"borrowedAt":"15.12.2020"},{"mediaNum":"12019237","mediaType":"book","isbn":"3-423-26231-1","author":"Falk, Rita","title":"Guglhupfgeschwader","numBorrowed":4,"borrowedAt":"30.11.2020"},{"mediaNum":"12019136","mediaType":"book","isbn":"3-8090-2705-7","author":"Edvardsson, Mattias","title":"Die Lüge","numBorrowed":4,"borrowedAt":"30.11.2020"},{"mediaNum":"12018209","mediaType":"book","isbn":"3-426-22605-7","author":"Buchholz, Simone","title":"Schwedenbitter","numBorrowed":4,"borrowedAt":"30.11.2020"},{"mediaNum":"12019240","mediaType":"book","isbn":"3-7457-0017-1","author":"Schlie, Tania","title":"Die Kirschen der Madame Richard","numBorrowed":4,"borrowedAt":"26.11.2020"},{"mediaNum":"12019272","mediaType":"book","isbn":"3-8105-3071-9","author":"Wünsche, Christiane","title":"Aber Töchter sind wir für immer","numBorrowed":4,"borrowedAt":"24.11.2020"},{"mediaNum":"12020179","mediaType":"book","isbn":"3-88769-595-X","author":"Nössler, Regina","title":"Die Putzhilfe","numBorrowed":4,"borrowedAt":"17.11.2020"},{"mediaNum":"12013219","mediaType":"book","isbn":"3-86612-207-1","author":"Ziegler, Ramona","title":"Herrgottswinkel","numBorrowed":4,"borrowedAt":"16.11.2020"},{"mediaNum":"12020002","mediaType":"book","isbn":"3-7341-0489-0","author":"Jacobs, Anne","title":"Das Gutshaus / Band 3","numBorrowed":4,"borrowedAt":"12.11.2020"},{"mediaNum":"12019153","mediaType":"book","isbn":"3-7341-0483-1","author":"Lee, Geneva","title":"Game of hearts","numBorrowed":4,"borrowedAt":"29.10.2020"},{"mediaNum":"12020178","mediaType":"book","isbn":"3-453-42425-5","author":"Lukas, Jana","title":"Die Mühlenschwestern - Bd. 1 / Die Liebe kennt den Weg zurück","numBorrowed":4,"borrowedAt":"20.10.2020"},{"mediaNum":"12019031","mediaType":"book","isbn":"3-550-08103-0","author":"Neuhaus, Nele","title":"Muttertag","numBorrowed":4,"borrowedAt":"09.10.2020"},{"mediaNum":"12019217","mediaType":"book","isbn":"3-404-17823-8","author":"Hülsmann, Petra","title":"Meistens kommt es anders, wenn man denkt","numBorrowed":4,"borrowedAt":"01.10.2020"},{"mediaNum":"12019027","mediaType":"book","isbn":"3-426-52076-1","author":"McFarlane, Mhairi","title":"Sowas kann auch nur mir passieren","numBorrowed":4,"borrowedAt":"01.10.2020"},{"mediaNum":"12019155","mediaType":"book","isbn":"3-7341-0481-5","author":"Lee, Geneva","title":"Game of Destiny","numBorrowed":4,"borrowedAt":"10.09.2020"},{"mediaNum":"12019154","mediaType":"book","isbn":"3-7341-0482-3","author":"Lee, Geneva","title":"Game of Passion","numBorrowed":4,"borrowedAt":"10.09.2020"},{"mediaNum":"12019347","mediaType":"book","isbn":"3-442-48574-6","author":"Winter, Claudia","title":"Das Honigmädchen","numBorrowed":4,"borrowedAt":"16.07.2020"},{"mediaNum":"12013316","mediaType":"book","isbn":"3-570-15572-2","author":"Fitzpatrick, Huntley / Galic, Anja","title":"Mein Sommer nebenan","numBorrowed":3,"borrowedAt":"28.01.2021"},{"mediaNum":"12020262","mediaType":"book","isbn":"3-453-42426-3","author":"Lukas, Jana","title":"Die Mühlenschwestern - Bd. 2 / Die Hoffnung wird dich finden","numBorrowed":3,"borrowedAt":"27.01.2021"},{"mediaNum":"12019336","mediaType":"book","isbn":"3-442-31447-X","author":"Riley, Lucinda / Hauser, Sonja / Schmidt, Sibylle / Wulfekamp, Ursula","title":"Die Sonnenschwester","numBorrowed":3,"borrowedAt":"26.01.2021"},{"mediaNum":"12018248","mediaType":"book","isbn":"3-442-31446-1","author":"Riley, Lucinda","title":"Die Mondschwester","numBorrowed":3,"borrowedAt":"26.01.2021"},{"mediaNum":"12020001","mediaType":"book","isbn":"3-426-28154-6","author":"Fitzek, Sebastian","title":"Das Geschenk","numBorrowed":3,"borrowedAt":"24.01.2021"},{"mediaNum":"12020160","mediaType":"book","isbn":"3-458-17792-2","author":"Dabos, Christelle","title":"Die Spiegelreisende Bd. 1","numBorrowed":3,"borrowedAt":"12.01.2021"},{"mediaNum":"12020031","mediaType":"book","isbn":"3-86612-418-X","author":"Förg, Nicola","title":"Scharfe Hunde","numBorrowed":3,"borrowedAt":"12.01.2021"},{"mediaNum":"12017197","mediaType":"book","isbn":"3-442-31445-3","author":"Riley, Lucinda","title":"Die Perlenschwester / Die sieben Schwestern Bd.4","numBorrowed":3,"borrowedAt":"12.01.2021"},{"mediaNum":"12018035","mediaType":"book","isbn":"3-492-31096-6","author":"Moriarty, Sinead","title":"Wie wir waren","numBorrowed":3,"borrowedAt":"05.01.2021"},{"mediaNum":"12014096","mediaType":"book","isbn":"3-8052-0484-1","author":"Willig, Lauren / Sandberg-Ciletti, Mechtild","title":"Ashford Park","numBorrowed":3,"borrowedAt":"05.01.2021"},{"mediaNum":"12020275","mediaType":"book","isbn":"3-257-07121-3","author":"Balzano, Marco","title":"Ich bleibe hier","numBorrowed":3,"borrowedAt":"26.12.2020"},{"mediaNum":"12020149","mediaType":"book","isbn":"3-446-26562-7","author":"Helfer, Monika","title":"Die Bagage","numBorrowed":3,"borrowedAt":"26.12.2020"},{"mediaNum":"12020263","mediaType":"book","isbn":"3-499-27674-7","author":"Freidank, Julia","title":"Das Brauhaus an der Isar - Bd. 2 / Im Sturm der Zeit","numBorrowed":3,"borrowedAt":"22.12.2020"},{"mediaNum":"12020100","mediaType":"book","isbn":"3-9616101-3-4","author":"Münzer, Hanni","title":"Solange es Schmetterlinge gibt","numBorrowed":3,"borrowedAt":"22.12.2020"},{"mediaNum":"12019265","mediaType":"book","isbn":"3-85179-377-3","author":"Huerta, Maxim","title":"Der Blumenladen der Mademoiselle Violeta","numBorrowed":3,"borrowedAt":"22.12.2020"},{"mediaNum":"12019141","mediaType":"book","isbn":"3-453-27213-7","author":"Grisham, John","title":"Das Bekenntnis","numBorrowed":3,"borrowedAt":"17.12.2020"},{"mediaNum":"12019243","mediaType":"book","isbn":"3-7408-0462-9","author":"Edelmann, Barbara","title":"Mordskrach","numBorrowed":3,"borrowedAt":"30.11.2020"},{"mediaNum":"12018037","mediaType":"book","isbn":"3-499-27213-X","author":"Korn, Carmen","title":"Töchter einer neuen Zeit","numBorrowed":3,"borrowedAt":"30.11.2020"},{"mediaNum":"12014101","mediaType":"book","isbn":"3-499-26736-5","author":"Moyes, Jojo / Fell, Karolina","title":"Weit weg und ganz nah","numBorrowed":3,"borrowedAt":"30.11.2020"},{"mediaNum":"12014052","mediaType":"book","isbn":"3442753937","author":"Börjlind, Cilla / Börjlind, Rolf / Berf, Paul","title":"Die Springflut","numBorrowed":3,"borrowedAt":"30.11.2020"},{"mediaNum":"12020162","mediaType":"book","isbn":"3-458-17827-9","author":"Dabos, Christelle","title":"Die Spiegelreisende Bd. 3","numBorrowed":3,"borrowedAt":"26.11.2020"},{"mediaNum":"12020161","mediaType":"book","isbn":"3-458-17826-0","author":"Dabos, Christelle","title":"Die Spiegelreisende Bd. 2","numBorrowed":3,"borrowedAt":"26.11.2020"},{"mediaNum":"12020152","mediaType":"book","isbn":"3-431-04125-6","author":"Lüders, Fenja","title":"Der Duft der weiten Welt","numBorrowed":3,"borrowedAt":"26.11.2020"},{"mediaNum":"12020253","mediaType":"book","isbn":"3-442-75860-2","author":"Jonasson, Ragnar","title":"Dunkel - HULDA Trilogie Band 1","numBorrowed":3,"borrowedAt":"19.11.2020"},{"mediaNum":"12016097","mediaType":"book","isbn":"3-423-21330-2","author":"Falk, Rita","title":"Winterkartoffelknödel / Franz Eberhofer Bd.1","numBorrowed":3,"borrowedAt":"17.11.2020"},{"mediaNum":"12019037","mediaType":"book","isbn":"3-7341-0488-2","author":"Jacobs, Anne","title":"Das Gutshaus / Band 2","numBorrowed":3,"borrowedAt":"12.11.2020"},{"mediaNum":"12020109","mediaType":"book","isbn":"3-86612-461-9","author":"Münzer, Hanni","title":"Heimat ist ein Sehnsuchtsort /Heimat-Saga Bd. 1","numBorrowed":3,"borrowedAt":"06.11.2020"},{"mediaNum":"12020112","mediaType":"book","isbn":"3-552-06326-9","author":"Freund, Rene","title":"Niemand weiß, wie spät es ist","numBorrowed":3,"borrowedAt":"29.10.2020"},{"mediaNum":"12019242","mediaType":"book","isbn":"3-7408-0171-9","author":"Edelmann, Barbara","title":"Mordsdepp","numBorrowed":3,"borrowedAt":"29.10.2020"},{"mediaNum":"12019046","mediaType":"book","isbn":"3-499-27639-9","author":"Moyes, Jojo","title":"Nächte, in denen Sturm aufzieht","numBorrowed":3,"borrowedAt":"29.10.2020"},{"mediaNum":"12020153","mediaType":"book","isbn":"3-423-26242-7","author":"Kara, Lesley","title":"Das Gerücht","numBorrowed":3,"borrowedAt":"22.10.2020"},{"mediaNum":"12015021","mediaType":"book","isbn":"3-426-19919-X","author":"Fitzek, Sebastian","title":"Passagier 23","numBorrowed":3,"borrowedAt":"20.10.2020"},{"mediaNum":"12020029","mediaType":"book","isbn":"3-8425-2025-5","author":"Seibold, Jürgen","title":"Zwei Likes für Lena","numBorrowed":3,"borrowedAt":"15.10.2020"},{"mediaNum":"12019116","mediaType":"book","isbn":"3-7466-3478-4","author":"Lauren, Christina","title":"Nichts als Liebe","numBorrowed":3,"borrowedAt":"09.10.2020"},{"mediaNum":"12020267","mediaType":"book","isbn":"3-86493-129-0","author":"Neumayer, Silke","title":"Schmetterlinge im Bauch sind die gefährlichsten Tiere der Welt","numBorrowed":3,"borrowedAt":"06.10.2020"},{"mediaNum":"12020015","mediaType":"book","isbn":"3-446-26191-5","author":"Bomann, Anne Cathrine","title":"Agathe","numBorrowed":3,"borrowedAt":"06.10.2020"},{"mediaNum":"12019025","mediaType":"book","isbn":"3-423-26206-0","author":"Heldt, Dora","title":"Drei Frauen am See","numBorrowed":3,"borrowedAt":"06.10.2020"},{"mediaNum":"12014182","mediaType":"book","isbn":"3-492-30391-9","author":"Lennox, Judith / Sandberg-Ciletti, Mechtild","title":"An einem Tag im Winter","numBorrowed":3,"borrowedAt":"01.10.2020"},{"mediaNum":"12019074","mediaType":"book","isbn":"3-7466-3393-1","author":"Klatt, Myriam","title":"Liebe geht immer","numBorrowed":3,"borrowedAt":"24.09.2020"},{"mediaNum":"12020046","mediaType":"book","isbn":"3-7645-3226-2","author":"Leibig, Timo","title":"Nanos - Sie kämpfen für die Freiheit","numBorrowed":3,"borrowedAt":"03.09.2020"},{"mediaNum":"12019117","mediaType":"book","isbn":"3-7466-3246-3","author":"Renk, Ulrike","title":"Das Lied der Störche / Ostpreußensaga Band 1","numBorrowed":3,"borrowedAt":"01.09.2020"},{"mediaNum":"12018077","mediaType":"book","isbn":"3-10-397351-9","author":"Colombani, Laetitia","title":"Der Zopf","numBorrowed":3,"borrowedAt":"01.09.2020"},{"mediaNum":"12018095","mediaType":"book","isbn":"3-7645-0546-X","author":"Sanders, Anne","title":"Sommer in St. Ives","numBorrowed":3,"borrowedAt":"18.08.2020"},{"mediaNum":"12014154","mediaType":"book","isbn":"3-442-38217-3","author":"Simses, Mary / Müller, Carolin","title":"Der Sommer der Blaubeeren","numBorrowed":3,"borrowedAt":"18.08.2020"},{"mediaNum":"12018151","mediaType":"book","isbn":"3-499-29060-X","author":"Maiwald, Jule","title":"Rette mich, wer kann","numBorrowed":3,"borrowedAt":"11.08.2020"},{"mediaNum":"12017181","mediaType":"book","isbn":"3-596-29764-8","author":"Wolf, Klaus-Peter","title":"Totenstille im Watt","numBorrowed":3,"borrowedAt":"04.08.2020"},{"mediaNum":"12020027","mediaType":"book","isbn":"3-458-17814-7","author":"Bürster, Helga","title":"Luzies Erbe","numBorrowed":3,"borrowedAt":"09.07.2020"},{"mediaNum":"12019130","mediaType":"book","isbn":"3-7363-0829-9","author":"Kneidl, Laura","title":"Someone New","numBorrowed":3,"borrowedAt":"02.06.2020"},{"mediaNum":"12018253","mediaType":"book","isbn":"3-499-27289-X","author":"Bergmann, Renate","title":"Wir brauchen viel mehr Schafe","numBorrowed":2,"borrowedAt":"28.01.2021"},{"mediaNum":"12018161","mediaType":"book","isbn":"3-570-31141-4","author":"Armentrout, Jennifer L","title":"Morgen lieb ich dich für immer","numBorrowed":2,"borrowedAt":"28.01.2021"},{"mediaNum":"12020055","mediaType":"book","isbn":"3-522-18483-1","author":"Huppertz, Nikola","title":"Woher ich meine Sommersprossen habe","numBorrowed":2,"borrowedAt":"26.01.2021"},{"mediaNum":"12010019","mediaType":"book","isbn":"3-401-06347-2","author":"Gier, Kerstin","title":"Saphirblau / Liebe geht durch alle Zeiten Bd.2","numBorrowed":2,"borrowedAt":"25.01.2021"},{"mediaNum":"12016206","mediaType":"book","isbn":"3-404-16999-9","author":"Follett, Ken / Schmidt, Dietmar / Schumacher, Rainer","title":"Winter der Welt","numBorrowed":2,"borrowedAt":"21.01.2021"},{"mediaNum":"12020005","mediaType":"book","isbn":"3-596-03634-8","author":"Wolf, Klaus-Peter","title":"Ostfriesen Fluch","numBorrowed":2,"borrowedAt":"19.01.2021"},{"mediaNum":"12018113","mediaType":"book","isbn":"3-550-08172-3","author":"Nesbø, Jo","title":"Durst / Harry Hole Bd.11","numBorrowed":2,"borrowedAt":"18.01.2021"},{"mediaNum":"12015250","mediaType":"book","isbn":"3-8052-5094-0","author":"Moyes, Jojo / Fell, Karolina","title":"Ein ganz neues Leben / Lou Bd.2","numBorrowed":2,"borrowedAt":"14.01.2021"},{"mediaNum":"12020093","mediaType":"book","isbn":"3-423-25361-4","author":"Halttunen, Elina / Kritzokat, Elina / Halttunen, Elina","title":"Alles gut auf der Insel - Großdruck","numBorrowed":2,"borrowedAt":"13.01.2021"},{"mediaNum":"12020045","mediaType":"book","isbn":"3-426-50411-1","author":"Lorentz, Iny","title":"Das Mädchen aus Apulien","numBorrowed":2,"borrowedAt":"12.01.2021"},{"mediaNum":"12016166","mediaType":"book","isbn":"3-7099-7822-X","author":"Gründel, Eva","title":"Mörderhitze","numBorrowed":2,"borrowedAt":"12.01.2021"}]}
