{"last_sync":"01.11.2019, 13:56 Uhr","books":[{"mediaNum":"12018035","mediaType":"book","isbn":"3-492-31096-6","author":"Moriarty, Sinead","title":"Wie wir waren","numBorrowed":9,"borrowedAt":"15.10.2019"},{"mediaNum":"12019046","mediaType":"book","isbn":"3-499-27639-9","author":"Moyes, Jojo","title":"Nächte, in denen Sturm aufzieht","numBorrowed":8,"borrowedAt":"08.10.2019"},{"mediaNum":"12018080","mediaType":"book","isbn":"3-550-08179-0","author":"Klüpfel, Volker","title":"Kluftinger / Kommissar Kluftinger Bd.10","numBorrowed":8,"borrowedAt":"26.09.2019"},{"mediaNum":"12018152","mediaType":"book","isbn":"3-492-30803-1","author":"Coleman, Rowan","title":"Im siebten Sommer","numBorrowed":8,"borrowedAt":"16.07.2019"},{"mediaNum":"12018136","mediaType":"book","isbn":"3-404-17690-1","author":"Hülsmann, Petra","title":"Wenn's einfach wär, würd's jeder machen","numBorrowed":7,"borrowedAt":"26.09.2019"},{"mediaNum":"12018001","mediaType":"book","isbn":"3-8052-5106-8","author":"Moyes, Jojo","title":"Mein Herz in zwei Welten","numBorrowed":7,"borrowedAt":"11.08.2019"},{"mediaNum":"12018095","mediaType":"book","isbn":"3-7645-0546-X","author":"Sanders, Anne","title":"Sommer in St. Ives","numBorrowed":7,"borrowedAt":"11.07.2019"},{"mediaNum":"12018094","mediaType":"book","isbn":"3-7857-6074-4","author":"Gier, Kerstin","title":"Die Mütter-Mafia 1","numBorrowed":7,"borrowedAt":"11.06.2019"},{"mediaNum":"12016181","mediaType":"book","isbn":"3-86396-081-5","author":"Leuze, Julie","title":"Für einen Sommer und immer","numBorrowed":6,"borrowedAt":"24.10.2019"},{"mediaNum":"12019031","mediaType":"book","isbn":"3-550-08103-0","author":"Neuhaus, Nele","title":"Muttertag","numBorrowed":6,"borrowedAt":"11.10.2019"},{"mediaNum":"12019025","mediaType":"book","isbn":"3-423-26206-0","author":"Heldt, Dora","title":"Drei Frauen am See","numBorrowed":6,"borrowedAt":"10.09.2019"},{"mediaNum":"12017194","mediaType":"book","isbn":"3-7466-3343-5","author":"Bennetto, Catherine / Schwaner, Teja / Hansen, Iris","title":"Und jetzt auch noch Liebe","numBorrowed":6,"borrowedAt":"06.08.2019"},{"mediaNum":"12018115","mediaType":"book","isbn":"3-328-10157-8","author":"Paulsen, Anna","title":"Liebe M. - Du bringst mein Herz zum Überlaufen","numBorrowed":6,"borrowedAt":"16.07.2019"},{"mediaNum":"12018110","mediaType":"book","isbn":"3-453-28522-0","author":"Marsh, Katie","title":"Die Liebe ist ein schlechter Verlierer","numBorrowed":6,"borrowedAt":"02.07.2019"},{"mediaNum":"12018114","mediaType":"book","isbn":"3-7645-0579-6","author":"Hein, Sybille","title":"Vorwärts küssen, rückwärts lieben","numBorrowed":6,"borrowedAt":"13.06.2019"},{"mediaNum":"12018077","mediaType":"book","isbn":"3-10-397351-9","author":"Colombani, Laetitia","title":"Der Zopf","numBorrowed":5,"borrowedAt":"24.10.2019"},{"mediaNum":"12015022","mediaType":"book","isbn":"3-453-29165-4","author":"Webb, Katherine / Volk, Katharina","title":"Das fremde Mädchen","numBorrowed":5,"borrowedAt":"24.10.2019"},{"mediaNum":"12019066","mediaType":"book","isbn":"3-404-17875-0","author":"Gier, Kerstin","title":"In Wahrheit wird viel mehr gelogen","numBorrowed":5,"borrowedAt":"22.10.2019"},{"mediaNum":"12019026","mediaType":"book","isbn":"3-442-48776-5","author":"Kinsella, Sophie","title":"Muss es denn gleich für immer sein","numBorrowed":5,"borrowedAt":"22.10.2019"},{"mediaNum":"12018248","mediaType":"book","isbn":"3-442-31446-1","author":"Riley, Lucinda","title":"Die Mondschwester","numBorrowed":5,"borrowedAt":"01.10.2019"},{"mediaNum":"12018256","mediaType":"book","isbn":"3-7341-0253-7","author":"Simses, Mary","title":"Der Sommer der Sternschnuppen","numBorrowed":5,"borrowedAt":"24.09.2019"},{"mediaNum":"12018210","mediaType":"book","isbn":"3-7341-0607-9","author":"Child, Lee","title":"Der letzte Befehl","numBorrowed":5,"borrowedAt":"24.09.2019"},{"mediaNum":"12016195","mediaType":"book","isbn":"3-404-17364-3","author":"Hülsmann, Petra","title":"Glück ist, wenn man trotzdem liebt","numBorrowed":5,"borrowedAt":"12.09.2019"},{"mediaNum":"12019098","mediaType":"book","isbn":"3-442-48738-2","author":"Walsh, Rosie","title":"Ohne ein einziges Wort","numBorrowed":5,"borrowedAt":"10.09.2019"},{"mediaNum":"12016112","mediaType":"book","isbn":"3-423-26058-0","author":"Ledig, Agnès / Marzolff, Sophia","title":"Kurz bevor das Glück beginnt","numBorrowed":5,"borrowedAt":"08.08.2019"},{"mediaNum":"12018205","mediaType":"book","isbn":"3-328-10169-1","author":"Douglas, Claire","title":"Missing","numBorrowed":5,"borrowedAt":"06.08.2019"},{"mediaNum":"12018117","mediaType":"book","isbn":"3-462-04887-2","author":"Ribeiro, Gil","title":"Lost in Fuseta","numBorrowed":5,"borrowedAt":"06.08.2019"},{"mediaNum":"12018054","mediaType":"book","isbn":"3-421-04666-2","author":"Quindlen, Anna / Handels, Tanja","title":"Ein Jahr auf dem Land","numBorrowed":5,"borrowedAt":"06.08.2019"},{"mediaNum":"12018029","mediaType":"book","isbn":"3-453-42115-9","author":"Simon, Teresa","title":"Die Oleanderfrauen","numBorrowed":5,"borrowedAt":"07.06.2019"},{"mediaNum":"12018121","mediaType":"book","isbn":"3-404-17148-9","author":"Moriarty, Liane / Schneider, Regina / Moriarty, Liane","title":"Das Geheimnis meines Mannes","numBorrowed":5,"borrowedAt":"20.12.2018"},{"mediaNum":"12017123","mediaType":"book","isbn":"3-404-17522-0","author":"Hülsmann, Petra","title":"Das Leben fällt, wohin es will","numBorrowed":4,"borrowedAt":"31.10.2019"},{"mediaNum":"12019028","mediaType":"book","isbn":"3-442-31499-2","author":"Lundberg, Sofia","title":"Das rote Adressbuch","numBorrowed":4,"borrowedAt":"24.10.2019"},{"mediaNum":"12018109","mediaType":"book","isbn":"3-453-42216-3","author":"McKenzie, Catherine","title":"Zerbrochenes Vertrauen","numBorrowed":4,"borrowedAt":"17.10.2019"},{"mediaNum":"12017124","mediaType":"book","isbn":"3-499-29042-1","author":"Liehr, Tom","title":"Landeier","numBorrowed":4,"borrowedAt":"17.10.2019"},{"mediaNum":"12016203","mediaType":"book","isbn":"3-404-17585-9","author":"Hülsmann, Petra","title":"Wenn Schmetterlinge Loopings fliegen","numBorrowed":4,"borrowedAt":"26.09.2019"},{"mediaNum":"12019142","mediaType":"book","isbn":"3-651-02574-8","author":"Maurer, Jörg","title":"Am Tatort bleibt man ungern liegen","numBorrowed":4,"borrowedAt":"24.09.2019"},{"mediaNum":"12017192","mediaType":"book","isbn":"3-499-27423-X","author":"Koch, Jessica","title":"Die Endlichkeit des Augenblicks","numBorrowed":4,"borrowedAt":"24.09.2019"},{"mediaNum":"12019027","mediaType":"book","isbn":"3-426-52076-1","author":"McFarlane, Mhairi","title":"Sowas kann auch nur mir passieren","numBorrowed":4,"borrowedAt":"12.09.2019"},{"mediaNum":"12018056","mediaType":"book","isbn":"3-351-05023-2","author":"Bjerg, Bov","title":"Auerhaus","numBorrowed":4,"borrowedAt":"10.09.2019"},{"mediaNum":"12017127","mediaType":"book","isbn":"3-86612-421-X","author":"Musso, Guillaume","title":"Das Mädchen aus Brooklyn","numBorrowed":4,"borrowedAt":"10.09.2019"},{"mediaNum":"12015250","mediaType":"book","isbn":"3-8052-5094-0","author":"Moyes, Jojo / Fell, Karolina","title":"Ein ganz neues Leben / Lou Bd.2","numBorrowed":4,"borrowedAt":"11.08.2019"},{"mediaNum":"12018022","mediaType":"book","isbn":"3-442-48573-8","author":"Winter, Claudia","title":"Die Wolkenfischerin","numBorrowed":4,"borrowedAt":"08.08.2019"},{"mediaNum":"12016096","mediaType":"book","isbn":"3-421-04582-8","author":"Dragnic, Natasa","title":"Immer wieder das Meer","numBorrowed":4,"borrowedAt":"08.08.2019"},{"mediaNum":"12019097","mediaType":"book","isbn":"3-453-35992-5","author":"Cohen, Julie","title":"Das geheime Glück","numBorrowed":4,"borrowedAt":"30.07.2019"},{"mediaNum":"12014212","mediaType":"book","isbn":"3-8105-1330-X","author":"Spielman, Lori Nelson / Fischer, Andrea","title":"Morgen kommt ein neuer Himmel","numBorrowed":4,"borrowedAt":"30.07.2019"},{"mediaNum":"12018240","mediaType":"book","isbn":"3-404-17656-1","author":"Gier, Kerstin","title":"Auf der anderen Seite ist das Gras viel Grüner","numBorrowed":4,"borrowedAt":"02.07.2019"},{"mediaNum":"12017196","mediaType":"book","isbn":"3-453-29205-7","author":"Riebe, Brigitte","title":"Marlenes Geheimnis","numBorrowed":4,"borrowedAt":"02.07.2019"},{"mediaNum":"12016094","mediaType":"book","isbn":"3-492-06012-9","author":"Clarke, Lucy / Franz, Claudia","title":"Der Sommer, in dem es zu schneien begann","numBorrowed":4,"borrowedAt":"02.07.2019"},{"mediaNum":"12018112","mediaType":"book","isbn":"3-548-61325-X","author":"Bréau, Adèle","title":"Fast perfekte Heldinnen","numBorrowed":4,"borrowedAt":"27.06.2019"},{"mediaNum":"12019013","mediaType":"book","isbn":"3-596-16932-1","author":"Kristin Marja Baldursdottir","title":"Die Eismalerin","numBorrowed":4,"borrowedAt":"25.06.2019"},{"mediaNum":"12019024","mediaType":"book","isbn":"3-453-47168-7","author":"Harris, Robert","title":"München - das Abkommen","numBorrowed":4,"borrowedAt":"28.05.2019"},{"mediaNum":"12018021","mediaType":"book","isbn":"3-453-42193-0","author":"Sparks, Nicholas","title":"Wenn du mich siehst","numBorrowed":4,"borrowedAt":"14.05.2019"},{"mediaNum":"12018158","mediaType":"book","isbn":"3-86612-446-5","author":"Musso, Guillaume / Hagedorn, Eliane / Runge, Bettina","title":"Das Atelier in Paris","numBorrowed":4,"borrowedAt":"09.05.2019"},{"mediaNum":"12017016","mediaType":"book","isbn":"3-499-26735-7","author":"Moyes, Jojo","title":"Im Schatten das Licht","numBorrowed":4,"borrowedAt":"09.05.2019"},{"mediaNum":"12017059","mediaType":"book","isbn":"3-453-26877-6","author":"Sparks, Nicholas","title":"Seit du bei mir bist","numBorrowed":4,"borrowedAt":"02.05.2019"},{"mediaNum":"12018171","mediaType":"book","isbn":"3-492-31153-9","author":"Colgan, Jenny","title":"Weihnachten in der kleinen Bäckerei am Strandweg","numBorrowed":4,"borrowedAt":"30.04.2019"},{"mediaNum":"12018203","mediaType":"book","isbn":"3-453-31716-5","author":"Liu, Cixin","title":"Die drei Sonnen","numBorrowed":4,"borrowedAt":"25.04.2019"},{"mediaNum":"12017089","mediaType":"book","isbn":"3-596-03658-5","author":"Martínez, Agustín","title":"Monteperdido","numBorrowed":4,"borrowedAt":"11.04.2019"},{"mediaNum":"12018092","mediaType":"book","isbn":"3-404-17350-3","author":"Müntefering, Mirjam","title":"Heute ist für immer","numBorrowed":4,"borrowedAt":"28.03.2019"},{"mediaNum":"12017048","mediaType":"book","isbn":"3-522-20220-1","author":"Zorn, Claire","title":"Klippen springen","numBorrowed":3,"borrowedAt":"31.10.2019"},{"mediaNum":"12016070","mediaType":"book","isbn":"3-426-19940-8","author":"Klüpfel, Volker","title":"In der ersten Reihe sieht man Meer","numBorrowed":3,"borrowedAt":"31.10.2019"},{"mediaNum":"12019125","mediaType":"book","isbn":"3-442-71674-8","author":"Cleveland, Karen","title":"Wahrheit gegen Wahrheit","numBorrowed":3,"borrowedAt":"29.10.2019"},{"mediaNum":"12014131","mediaType":"book","isbn":"3-8414-2167-9","author":"Gier, Kerstin","title":"Das zweite Buch der Träume / Silber Trilogie Bd.2","numBorrowed":3,"borrowedAt":"27.10.2019"},{"mediaNum":"12015259","mediaType":"book","isbn":"3-442-31394-5","author":"Riley, Lucinda / Hauser, Sonja","title":"Die sieben Schwestern","numBorrowed":3,"borrowedAt":"25.10.2019"},{"mediaNum":"12019237","mediaType":"book","isbn":"3-423-26231-1","author":"Falk, Rita","title":"Guglhupfgeschwader","numBorrowed":3,"borrowedAt":"24.10.2019"},{"mediaNum":"12013076","mediaType":"book","isbn":"3-8414-2105-9","author":"Gier, Kerstin","title":"Silber","numBorrowed":3,"borrowedAt":"24.10.2019"},{"mediaNum":"12015269","mediaType":"book","isbn":"3-9545168-0-2","author":"Edelmann, Barbara","title":"Mordsrausch","numBorrowed":3,"borrowedAt":"22.10.2019"},{"mediaNum":"12017161","mediaType":"book","isbn":"3-8333-1053-7","author":"Colgan, Jenny","title":"Die kleine Bäckerei am Strandweg","numBorrowed":3,"borrowedAt":"17.10.2019"},{"mediaNum":"12015032","mediaType":"book","isbn":"3-8052-5031-2","author":"Poznanski, Ursula","title":"Fünf","numBorrowed":3,"borrowedAt":"17.10.2019"},{"mediaNum":"12017181","mediaType":"book","isbn":"3-596-29764-8","author":"Wolf, Klaus-Peter","title":"Totenstille im Watt","numBorrowed":3,"borrowedAt":"10.10.2019"},{"mediaNum":"12016167","mediaType":"book","isbn":"3-442-48405-7","author":"Riley, Lucinda","title":"Helenas Geheimnis","numBorrowed":3,"borrowedAt":"10.10.2019"},{"mediaNum":"12014096","mediaType":"book","isbn":"3-8052-0484-1","author":"Willig, Lauren / Sandberg-Ciletti, Mechtild","title":"Ashford Park","numBorrowed":3,"borrowedAt":"10.10.2019"},{"mediaNum":"12019119","mediaType":"book","isbn":"3-7466-3356-7","author":"Renk, Ulrike","title":"Die Zeit der Kraniche / Ostpreußensaga Band 3","numBorrowed":3,"borrowedAt":"08.10.2019"},{"mediaNum":"12019118","mediaType":"book","isbn":"3-7466-3351-6","author":"Renk, Ulrike","title":"Die Jahre der Schwalben / Ostpreußensaga Band 2","numBorrowed":3,"borrowedAt":"08.10.2019"},{"mediaNum":"12019117","mediaType":"book","isbn":"3-7466-3246-3","author":"Renk, Ulrike","title":"Das Lied der Störche / Ostpreußensaga Band 1","numBorrowed":3,"borrowedAt":"08.10.2019"},{"mediaNum":"12013010","mediaType":"book","isbn":"3-442-31270-1","author":"Fielding, Joy / Lutze, Kristian","title":"Das Herz des Bösen","numBorrowed":3,"borrowedAt":"08.10.2019"},{"mediaNum":"12018057","mediaType":"book","isbn":"3-570-10195-9","author":"Doughty, Louise / Arz, Astrid","title":"Ein Schritt zu weit","numBorrowed":3,"borrowedAt":"01.10.2019"},{"mediaNum":"12008066","mediaType":"book","isbn":"3-7891-4738-9","author":"Sandén, Marten","title":"Mias Glück","numBorrowed":3,"borrowedAt":"27.09.2019"},{"mediaNum":"12019071","mediaType":"book","isbn":"3-401-60167-9","author":"Thiemeyer, Thomas","title":"Evolution - Die Stadt der Überlebenden","numBorrowed":3,"borrowedAt":"10.09.2019"},{"mediaNum":"12018003","mediaType":"book","isbn":"3-9596704-6-X","author":"Erzberg, Tim","title":"Hell-Go-Land","numBorrowed":3,"borrowedAt":"10.09.2019"},{"mediaNum":"12017009","mediaType":"book","isbn":"3-423-26127-7","author":"Falk, Rita","title":"Weißwurstconnection","numBorrowed":3,"borrowedAt":"10.09.2019"},{"mediaNum":"12014210","mediaType":"book","isbn":"3-426-51380-3","author":"Ahrens, Renate","title":"Seit jenem Moment","numBorrowed":3,"borrowedAt":"10.09.2019"},{"mediaNum":"12019120","mediaType":"book","isbn":"3-499-27292-X","author":"Bloom, Franka","title":"Anfang 40 - Ende offen","numBorrowed":3,"borrowedAt":"08.08.2019"},{"mediaNum":"12019131","mediaType":"book","isbn":"3-7363-0556-7","author":"Kasten, Mona","title":"Save me","numBorrowed":3,"borrowedAt":"06.08.2019"},{"mediaNum":"12019128","mediaType":"book","isbn":"3-8105-3038-7","author":"Baier, Hiltrud","title":"Helle Tage, helle Nächte","numBorrowed":3,"borrowedAt":"06.08.2019"},{"mediaNum":"12019037","mediaType":"book","isbn":"3-7341-0488-2","author":"Jacobs, Anne","title":"Stürmische Zeiten","numBorrowed":3,"borrowedAt":"06.08.2019"},{"mediaNum":"12018093","mediaType":"book","isbn":"3-442-48531-2","author":"Legardinier, Gilles / Heinemann, Doris","title":"Monsieur Thomas und das Geschenk der Liebe","numBorrowed":3,"borrowedAt":"06.08.2019"},{"mediaNum":"12018038","mediaType":"book","isbn":"3-7341-0327-4","author":"Jacobs, Anne","title":"Glanzvolle Zeiten","numBorrowed":3,"borrowedAt":"06.08.2019"},{"mediaNum":"12018232","mediaType":"book","isbn":"3-442-74926-3","author":"Aichner, Bernhard","title":"Totenfrau","numBorrowed":3,"borrowedAt":"01.08.2019"},{"mediaNum":"12018249","mediaType":"book","isbn":"3-463-40684-5","author":"Korn, Carmen","title":"Zeitenwende","numBorrowed":3,"borrowedAt":"30.07.2019"},{"mediaNum":"12014320","mediaType":"book","isbn":"3-453-26652-8","author":"Sparks, Nicholas / Zöfel, Adelheid / Sparks, Nicholas","title":"Mit dir an meiner Seite","numBorrowed":3,"borrowedAt":"30.07.2019"},{"mediaNum":"12016227","mediaType":"book","isbn":"3-8105-2471-9","author":"Spielman, Lori Nelson","title":"Und nebenan warten die Sterne","numBorrowed":3,"borrowedAt":"16.07.2019"},{"mediaNum":"12015130","mediaType":"book","isbn":"3-547-71193-2","author":"Ruppert, Astrid","title":"Ziemlich beste Freundinnen","numBorrowed":3,"borrowedAt":"16.07.2019"},{"mediaNum":"12019116","mediaType":"book","isbn":"3-7466-3478-4","author":"Lauren, Christina","title":"Nichts als Liebe","numBorrowed":3,"borrowedAt":"11.07.2019"},{"mediaNum":"12015180","mediaType":"book","isbn":"3-442-38156-8","author":"Enger, Thomas / Frauenlob, Günther / Dörries, Maike","title":"Vergiftet","numBorrowed":3,"borrowedAt":"09.07.2019"},{"mediaNum":"12019034","mediaType":"book","isbn":"3-651-02562-4","author":"French, Tana / Wasel, Ulrike / Timmermann, Klaus","title":"Der dunkle Garten","numBorrowed":3,"borrowedAt":"02.07.2019"},{"mediaNum":"12017122","mediaType":"book","isbn":"3-404-17460-7","author":"Thomas, Jo","title":"Ein Sommer wie kein zweiter","numBorrowed":3,"borrowedAt":"02.07.2019"},{"mediaNum":"12017100","mediaType":"book","isbn":"3-442-71417-6","author":"Raabe, Melanie","title":"Die Falle","numBorrowed":3,"borrowedAt":"18.06.2019"},{"mediaNum":"12013204","mediaType":"book","isbn":"3-378-00680-3","author":"Edwards, Kim","title":"Die Tochter des Fotografen","numBorrowed":3,"borrowedAt":"11.06.2019"},{"mediaNum":"12017118","mediaType":"book","isbn":"3-8090-2663-8","author":"Ohlsson, Kristina","title":"Schwesterherz","numBorrowed":3,"borrowedAt":"06.06.2019"}]}
