{"last_sync":"24.07.2020, 16:42 Uhr","books":[{"mediaNum":"12019085","mediaType":"book","isbn":"3-944321-46-4","author":"Die Allgäuerin","title":"So backt die Allgäuerin","numBorrowed":8,"borrowedAt":"18.06.2020"},{"mediaNum":"12018060","mediaType":"book","isbn":"3-426-21433-4","author":"Trinkwalder, Sina","title":"Im nächsten Leben ist zu spät","numBorrowed":8,"borrowedAt":"05.03.2020"},{"mediaNum":"12018160","mediaType":"book","isbn":"3-03-800975-X","author":"Schilling, Claudia","title":"Hin und weg","numBorrowed":8,"borrowedAt":"04.02.2020"},{"mediaNum":"12018146","mediaType":"book","isbn":"3-8338-6540-7","author":"Bracht, Petra","title":"Intervallfasten","numBorrowed":8,"borrowedAt":"18.07.2019"},{"mediaNum":"12017062","mediaType":"book","isbn":"3-517-09535-4","author":"Gronau, Daniela","title":"Das große Kochbuch für den Thermomix","numBorrowed":7,"borrowedAt":"02.07.2020"},{"mediaNum":"12019090","mediaType":"book","isbn":"3-946658-00-8","author":"smarticular","title":"Fünf Hausmittel ersetzen eine Drogerie","numBorrowed":6,"borrowedAt":"09.07.2020"},{"mediaNum":"12018129","mediaType":"book","isbn":"3-944321-52-9","author":"Die Allgäuerin","title":"Kaffeeklatsch","numBorrowed":6,"borrowedAt":"30.04.2020"},{"mediaNum":"12017063","mediaType":"book","isbn":"3-7724-8018-7","author":"Schlaich, Jasmin","title":"Süßes mit Kuss","numBorrowed":6,"borrowedAt":"16.02.2020"},{"mediaNum":"12019084","mediaType":"book","isbn":"3-9910024-1-8","author":"Borsche, Lorenz","title":"Zucker","numBorrowed":6,"borrowedAt":"22.10.2019"},{"mediaNum":"12019215","mediaType":"book","isbn":"3-9621101-3-5","author":"","title":"Gesunde Ernährung auf mediterrane Art","numBorrowed":5,"borrowedAt":"02.07.2020"},{"mediaNum":"12018139","mediaType":"book","isbn":"3-7716-4657-X","author":"Wiedemann, Christina","title":"Spiralize it!: Spaghetti aus Obst und Gemüse","numBorrowed":5,"borrowedAt":"02.06.2020"},{"mediaNum":"12019047","mediaType":"book","isbn":"3-466-37208-9","author":"Schießler, Rainer M.","title":"Jessas, Maria und Josef","numBorrowed":5,"borrowedAt":"19.05.2020"},{"mediaNum":"12015158","mediaType":"book","isbn":"3-7633-3074-7","author":"Soeffker, Eduard","title":"Erlebniswandern mit Kindern - Allgäu","numBorrowed":5,"borrowedAt":"19.05.2020"},{"mediaNum":"12017065","mediaType":"book","isbn":"3-89883-578-2","author":"Mutschelknaus, Katja","title":"LandfrauenKüche","numBorrowed":5,"borrowedAt":"27.03.2020"},{"mediaNum":"12015281","mediaType":"book","isbn":"3-7724-8004-7","author":"Blaschke, Katrin / Mayer, Katharina","title":"Kuchentratsch","numBorrowed":5,"borrowedAt":"27.03.2020"},{"mediaNum":"12017064","mediaType":"book","isbn":"3-625-17818-4","author":"Peters, Anne","title":"Low Carb - das große Backbuch","numBorrowed":5,"borrowedAt":"05.03.2020"},{"mediaNum":"12019113","mediaType":null,"isbn":"","author":"AVA Verlag","title":"Die Allgäuerin","numBorrowed":5,"borrowedAt":"11.02.2020"},{"mediaNum":"12014201","mediaType":"book","isbn":"3-8310-2440-5","author":"Blashford-Snell, Victoria","title":"Fingerfood","numBorrowed":5,"borrowedAt":"06.02.2020"},{"mediaNum":"12018212","mediaType":"book","isbn":"3-86334-209-7","author":"Schacht, Christopher","title":"Mit 50 Euro um die Welt","numBorrowed":5,"borrowedAt":"30.01.2020"},{"mediaNum":"12016105","mediaType":"book","isbn":"3-89604-959-3","author":"Stadler, Veronika","title":"Kinder-Geburtstags-Kuchen","numBorrowed":5,"borrowedAt":"09.01.2020"},{"mediaNum":"12019091","mediaType":"book","isbn":"3-86581-784-X","author":"Bunk, Anneliese","title":"Besser leben ohne Plastik","numBorrowed":5,"borrowedAt":"26.11.2019"},{"mediaNum":"12018215","mediaType":"book","isbn":"3-8338-2272-4","author":"Spitz, Jörg","title":"Superhormon Vitamin D","numBorrowed":5,"borrowedAt":"31.10.2019"},{"mediaNum":"12018216","mediaType":"book","isbn":"3-458-17698-5","author":"Michalsen, Andreas","title":"Heilen mit der Kraft der Natur","numBorrowed":5,"borrowedAt":"08.08.2019"},{"mediaNum":"12019191","mediaType":"book","isbn":"3-89859-460-2","author":"Kettl-Römer, Barbara","title":"Allgäu mit Kindern","numBorrowed":4,"borrowedAt":"14.07.2020"},{"mediaNum":"12016146","mediaType":"book","isbn":"3-517-09365-3","author":"Axt-Gadermann, Michaela","title":"Schlank mit Darm","numBorrowed":4,"borrowedAt":"12.06.2020"},{"mediaNum":"12019105","mediaType":"book","isbn":"3-943471-04-7","author":"Kirstein, Susanne","title":"Ich bring' Dich zum Kochen - vegetarisch","numBorrowed":4,"borrowedAt":"03.06.2020"},{"mediaNum":"12019275","mediaType":"book","isbn":"3-7106-0260-2","author":"Macedonia, Manuela","title":"Beweg dich! Und dein Gehirn sagt Danke","numBorrowed":4,"borrowedAt":"02.04.2020"},{"mediaNum":"12019095","mediaType":"book","isbn":"3-944321-70-7","author":"Die Allgäuerin","title":"Kaffeeklatsch","numBorrowed":4,"borrowedAt":"27.03.2020"},{"mediaNum":"12019087","mediaType":null,"isbn":"4021729311044","author":"Meine Familie & Ich books","title":"Asia-Küche","numBorrowed":4,"borrowedAt":"27.03.2020"},{"mediaNum":"12015080","mediaType":"book","isbn":"3-517-09295-9","author":"","title":"Zauberhafte Backideen","numBorrowed":4,"borrowedAt":"11.02.2020"},{"mediaNum":"12015252","mediaType":"book","isbn":"3-8338-4177-X","author":"Bodensteiner, Susanne / Binner, Mona","title":"Seelenfutter vegetarisch","numBorrowed":4,"borrowedAt":"06.02.2020"},{"mediaNum":"12018134","mediaType":"book","isbn":"3-7724-7468-3","author":"Du, Kai Daniel / Behnke, Benjamin","title":"Trick 17 - Küche","numBorrowed":4,"borrowedAt":"21.01.2020"},{"mediaNum":"12015160","mediaType":"book","isbn":"3-86246-288-9","author":"Eberhard, Frank / Kaufmann, Susanne / Irlinger, Bernhard / Meier, Markus","title":"Meine Lieblings-Alm im Allgäu","numBorrowed":4,"borrowedAt":"19.09.2019"},{"mediaNum":"12015258","mediaType":"book","isbn":"3-7724-6217-0","author":"Annika","title":"Handlettering","numBorrowed":4,"borrowedAt":"12.09.2019"},{"mediaNum":"12017036","mediaType":"book","isbn":"3-945429-45-5","author":"Wagener, Klaus","title":"Naturwerkstatt","numBorrowed":4,"borrowedAt":"10.09.2019"},{"mediaNum":"12018145","mediaType":"book","isbn":"3-426-27754-9","author":"Steckel, Hanno","title":"Genial beweglich","numBorrowed":4,"borrowedAt":"11.08.2019"},{"mediaNum":"12019194","mediaType":"book","isbn":"3-8425-2067-0","author":"Grimmler, Benedikt","title":"Radtouren für Langschläfer - Bodensee","numBorrowed":3,"borrowedAt":"23.07.2020"},{"mediaNum":"12019198","mediaType":"book","isbn":"3-944321-63-4","author":"Buck, Dieter","title":"Spritztouren im Allgäu","numBorrowed":3,"borrowedAt":"21.07.2020"},{"mediaNum":"12019195","mediaType":"book","isbn":"3-7700-2034-0","author":"Blasche, Thomas","title":"Glücksorte am Bodensee","numBorrowed":3,"borrowedAt":"14.07.2020"},{"mediaNum":"12019214","mediaType":"book","isbn":"3-7667-2038-4","author":"Lemke, Lisa","title":"Sommerküche","numBorrowed":3,"borrowedAt":"02.07.2020"},{"mediaNum":"12014125","mediaType":"book","isbn":"3-550-08041-7","author":"Enders, Giulia","title":"Darm mit Charme","numBorrowed":3,"borrowedAt":"23.06.2020"},{"mediaNum":"12009912","mediaType":"book","isbn":"3-7658-4096-3","author":"Bauregger, Heinrich","title":"Die schönsten Wanderungen mit Kindern im Allgäu","numBorrowed":3,"borrowedAt":"23.06.2020"},{"mediaNum":"12019197","mediaType":"book","isbn":"3-7343-1434-8","author":"Kellermann, Monika","title":"Glücksmomente Gardasee","numBorrowed":3,"borrowedAt":"16.06.2020"},{"mediaNum":"12019092","mediaType":"book","isbn":"3-453-60491-1","author":"Windscheid, Leon","title":"Hey Hirn","numBorrowed":3,"borrowedAt":"16.06.2020"},{"mediaNum":"12019193","mediaType":"book","isbn":"3-7343-1259-0","author":"Bahnmüller, Lisa","title":"Das Allgäu erfahren","numBorrowed":3,"borrowedAt":"04.06.2020"},{"mediaNum":"12016061","mediaType":"book","isbn":"3-473-55370-0","author":"Schiller, Marlies","title":"Tolle neue Bastelideen für Ostern","numBorrowed":3,"borrowedAt":"19.03.2020"},{"mediaNum":"12016062","mediaType":"book","isbn":"3-473-55370-0","author":"Schiller, Marlies","title":"Tolle neue Bastelideen für Ostern","numBorrowed":3,"borrowedAt":"13.03.2020"},{"mediaNum":"12019320","mediaType":"book","isbn":"3-10-397482-5","author":"Snowden, Edward J","title":"Permanent Record","numBorrowed":3,"borrowedAt":"16.02.2020"},{"mediaNum":"12019309","mediaType":"book","isbn":"3-7066-2662-4","author":"Aust, Johanna","title":"Die besten Weihnachtskekse","numBorrowed":3,"borrowedAt":"13.12.2019"},{"mediaNum":"12012009","mediaType":"book","isbn":"3-86244-215-2","author":"Kobr, Silke / Lang, Coco","title":"Süße Weihnachtsbäckerei","numBorrowed":3,"borrowedAt":"13.12.2019"},{"mediaNum":"12009020","mediaType":"book","isbn":"3-419-54113-9","author":"Herrenknecht, Kathja / Steinmeyer, Martha / Utermarck, Birgit / Schmotz, Christoph / Windhüfel, Gisa","title":"Adventskalender","numBorrowed":3,"borrowedAt":"13.12.2019"},{"mediaNum":"12019308","mediaType":"book","isbn":"3-944321-29-4","author":"","title":"Das Allgäu backt zur Weihnachtszeit","numBorrowed":3,"borrowedAt":"10.12.2019"},{"mediaNum":"12017223","mediaType":"book","isbn":"3-7724-7778-X","author":"Deges, Pia","title":"Fröhliche DIYnachten","numBorrowed":3,"borrowedAt":"10.12.2019"},{"mediaNum":"12015300","mediaType":"book","isbn":"3-7724-5969-2","author":"Sanwald, Natascha / Hoernisch, Andreas","title":"Merry Christmas","numBorrowed":3,"borrowedAt":"10.12.2019"},{"mediaNum":"12018135","mediaType":"book","isbn":"3-9545189-2-9","author":"Kühn, Tosca Maria","title":"Das große Weihnachtsbuch Allgäu","numBorrowed":3,"borrowedAt":"05.12.2019"},{"mediaNum":"12019094","mediaType":"book","isbn":"3-7724-7726-7","author":"Volkmer, Ina","title":"Trick 17 - Nachhaltig leben","numBorrowed":3,"borrowedAt":"26.11.2019"},{"mediaNum":"12014714","mediaType":null,"isbn":"4198870905009","author":"Landlust","title":"Landlust Weihnachten","numBorrowed":3,"borrowedAt":"26.11.2019"},{"mediaNum":"12019111","mediaType":"book","isbn":"3-570-10319-6","author":"Kast, Bas","title":"Der Ernährungskompass","numBorrowed":3,"borrowedAt":"24.10.2019"},{"mediaNum":"12019109","mediaType":"book","isbn":"3-424-63107-8","author":"Stahl, Stefanie","title":"Das Kind in dir muss Heimat finden","numBorrowed":3,"borrowedAt":"26.09.2019"},{"mediaNum":"12019021","mediaType":"book","isbn":"3-453-20147-7","author":"Kiechle, Marion","title":"Tag für Tag jünger","numBorrowed":3,"borrowedAt":"22.09.2019"},{"mediaNum":"12019048","mediaType":"book","isbn":"3-7724-7927-8","author":"Rötters, Nina","title":"Vorlagenmappe Fensterdeko mit dem Kreidemarker - Handlettering. Inkl. Original Kreidemarker von Kreul und Schablonen","numBorrowed":3,"borrowedAt":"12.09.2019"},{"mediaNum":"12019035","mediaType":"book","isbn":"3-328-60021-3","author":"Lesch, Harald","title":"Wenn nicht jetzt, wann dann?","numBorrowed":3,"borrowedAt":"11.08.2019"},{"mediaNum":"12018147","mediaType":"book","isbn":"3-8338-5872-9","author":"Kullmann, Folko","title":"Garten step-by-step","numBorrowed":3,"borrowedAt":"18.07.2019"},{"mediaNum":"12016039","mediaType":"book","isbn":"3-8354-1353-8","author":"Kullmann, Folko","title":"Garten-Projekte für Selbermacher","numBorrowed":3,"borrowedAt":"11.04.2019"},{"mediaNum":"12019248","mediaType":"book","isbn":"3-453-28095-4","author":"Wohlleben, Peter","title":"Das geheime Band zwischen Mensch und Natur","numBorrowed":2,"borrowedAt":"21.07.2020"},{"mediaNum":"12015097","mediaType":"book","isbn":"3-86873-728-6","author":"Gleeson, Erin / Neuberger, Helmut","title":"Ein Fest im Grünen","numBorrowed":2,"borrowedAt":"21.07.2020"},{"mediaNum":"12016188","mediaType":"book","isbn":"3-9545134-3-9","author":"Ziegler, Cornelia / Sindermann, Chris","title":"111 Orte im Allgäu, die man gesehen haben muss","numBorrowed":2,"borrowedAt":"07.07.2020"},{"mediaNum":"12020073","mediaType":"book","isbn":"3-8186-0706-0","author":"Peitz, Beate / Peitz, Leopold / Bauer, Wilhelm","title":"Hühner in meinem Garten","numBorrowed":2,"borrowedAt":"30.06.2020"},{"mediaNum":"12015098","mediaType":"book","isbn":"3-8310-2578-9","author":"Skowronek, Julia / Sporrer, Brigitte","title":"Biergartenkochbuch","numBorrowed":2,"borrowedAt":"30.06.2020"},{"mediaNum":"12019349","mediaType":"book","isbn":"3-7481-2848-7","author":"Metzeler, Pam","title":"Dark Way","numBorrowed":2,"borrowedAt":"23.06.2020"},{"mediaNum":"12019192","mediaType":"book","isbn":"3-86246-092-4","author":"Theml, Robert","title":"Die schönsten Erlebnistouren für Zwergerl im Allgäu","numBorrowed":2,"borrowedAt":"23.06.2020"},{"mediaNum":"12015282","mediaType":"book","isbn":"3-7724-7919-7","author":"Charlier, Nathalie / Duron, Sofie","title":"Meine Tasche","numBorrowed":2,"borrowedAt":"23.06.2020"},{"mediaNum":"12020081","mediaType":"book","isbn":"3-8310-3900-3","author":"Richards, Huw","title":"Hochbeet","numBorrowed":2,"borrowedAt":"18.06.2020"},{"mediaNum":"12020138","mediaType":"book","isbn":"3-86334-222-4","author":"Fusaro, Giuseppe \"Pino","title":"Pellegrino - Vom Playboy zum Pilger","numBorrowed":2,"borrowedAt":"16.06.2020"},{"mediaNum":"12020139","mediaType":"book","isbn":"3-492-06177-X","author":"Thiel, Jeremias","title":"Kein Pausenbrot, keine Kindheit, keine Chance","numBorrowed":2,"borrowedAt":"12.06.2020"},{"mediaNum":"12019199","mediaType":"book","isbn":"3-944321-72-3","author":"Buck, Dieter","title":"Faszination Allgäuer Alphütten","numBorrowed":2,"borrowedAt":"09.06.2020"},{"mediaNum":"12020051","mediaType":"book","isbn":"3-943793-77-X","author":"Büttner, Peter","title":"Sprechstunde Kinderarzt","numBorrowed":2,"borrowedAt":"04.06.2020"},{"mediaNum":"12017187","mediaType":"book","isbn":"3-03-800790-0","author":"Hofer, Julia / Schneider, Andre","title":"Das große Familienkochbuch","numBorrowed":2,"borrowedAt":"02.06.2020"},{"mediaNum":"12002018","mediaType":"book","isbn":"3-8320-8682-X","author":"Lang, Elisabeth / Kargl, Christian","title":"Grillen","numBorrowed":2,"borrowedAt":"12.05.2020"},{"mediaNum":"12012008","mediaType":"book","isbn":"3-86244-154-7","author":"Richardson, Rosamond","title":"Was man früher noch wusste","numBorrowed":2,"borrowedAt":"30.04.2020"},{"mediaNum":"12019311","mediaType":"book","isbn":"3-9634001-0-2","author":"Käßmann, Margot","title":"Schöne Aussichten auf die besten Jahre","numBorrowed":2,"borrowedAt":"07.04.2020"},{"mediaNum":"11994056","mediaType":"book","isbn":"3-8043-0269-6","author":"Pfeiffer, Christina","title":"Kinderleichtes Osterbasteln","numBorrowed":2,"borrowedAt":"13.03.2020"},{"mediaNum":"12019323","mediaType":"book","isbn":"3-9596111-3-7","author":"Henze, Christian","title":"So kocht man heute","numBorrowed":2,"borrowedAt":"05.03.2020"},{"mediaNum":"12014202","mediaType":"book","isbn":"3-8310-2465-0","author":"Bretherton, Caroline / Vance, Peggy","title":"Tartes, Quiches und Pies","numBorrowed":2,"borrowedAt":"18.02.2020"},{"mediaNum":"12019288","mediaType":"book","isbn":"3-492-06099-4","author":"Schönian, Valerie","title":"Halleluja","numBorrowed":2,"borrowedAt":"13.02.2020"},{"mediaNum":"12019045","mediaType":"book","isbn":"3-8310-3372-2","author":"Harvey, Karen","title":"Kinderschminken leicht gemacht","numBorrowed":2,"borrowedAt":"11.02.2020"},{"mediaNum":"12014203","mediaType":"book","isbn":"3-8388-3475-5","author":"Auenhammer, Gerlinde / Krieg, Roland / Dawidowski, Marion / Kipp, Angelika","title":"Deko-Ideen Natur","numBorrowed":2,"borrowedAt":"11.02.2020"},{"mediaNum":"12009013","mediaType":"book","isbn":"3-7654-4478-2","author":"Taschner, Wolfgang / Reimer, Michael","title":"Winterwandern im Allgäu","numBorrowed":2,"borrowedAt":"11.02.2020"},{"mediaNum":"12019255","mediaType":"book","isbn":"3-492-40573-8","author":"Hoepner, Hansen / Hoepner, Paul / Müller, Marie-Sophie","title":"Zwei nach Shanghai","numBorrowed":2,"borrowedAt":"30.01.2020"},{"mediaNum":"12018088","mediaType":"book","isbn":"3-89029-483-9","author":"Carrel, Francois","title":"Alexander und Thomas Huber","numBorrowed":2,"borrowedAt":"30.01.2020"},{"mediaNum":"12019267","mediaType":"book","isbn":"3-9588924-9-3","author":"Martin, Nick","title":"Die geilste Lücke im Lebenslauf","numBorrowed":2,"borrowedAt":"07.01.2020"},{"mediaNum":"12013232","mediaType":"book","isbn":"3-446-23100-5","author":"Werner-Lobo, Klaus","title":"Uns gehört die Welt","numBorrowed":2,"borrowedAt":"07.01.2020"},{"mediaNum":"12014222","mediaType":"book","isbn":"3-572-08073-8","author":"Neuner, Bernd / Newedel, Karl","title":"Plätzchen & Stollen","numBorrowed":2,"borrowedAt":"13.12.2019"},{"mediaNum":"12009027","mediaType":"book","isbn":"3-7670-0682-0","author":"Rabeler, Anke / Lüning, Sabine","title":"Dr. Oetker - Plätzchen","numBorrowed":2,"borrowedAt":"13.12.2019"},{"mediaNum":"12019281","mediaType":"book","isbn":"3-03-848026-6","author":"Müller, Josef","title":"Ziemlich bester Schurke","numBorrowed":2,"borrowedAt":"10.12.2019"},{"mediaNum":"12019089","mediaType":"book","isbn":"3-8312-0471-3","author":"Dellert, Louisa","title":"Mein Herz schlägt grün","numBorrowed":2,"borrowedAt":"10.12.2019"},{"mediaNum":"12015253","mediaType":"book","isbn":"3-8338-2629-0","author":"Bodensteiner, Susanne / Schlimm, Sabine / Hoersch, Julia","title":"Seelenfutter","numBorrowed":2,"borrowedAt":"05.12.2019"},{"mediaNum":"12015280","mediaType":"book","isbn":"3-88117-939-9","author":"Nieschlag, Lisa / Cawley, Julia / Wentrup, Lars","title":"Advent, Advent","numBorrowed":2,"borrowedAt":"28.11.2019"},{"mediaNum":"12013412","mediaType":"book","isbn":"3-8354-1045-8","author":"Graumann, Katja / Schütz, Anke","title":"Das Weihnachtsdeko-Buch","numBorrowed":2,"borrowedAt":"24.11.2019"},{"mediaNum":"12013175","mediaType":"book","isbn":"3-8425-1133-7","author":"Sonntag, Christoph","title":"AZNZ","numBorrowed":2,"borrowedAt":"24.11.2019"}]}
